pyaqueduct/__init__.py
pyaqueduct/api.py
pyaqueduct/client/__init__.py
pyaqueduct/client/client.py
pyaqueduct/client/experiment_types.py
pyaqueduct/client/extension_types.py
pyaqueduct/exceptions.py
pyaqueduct/experiment.py
pyaqueduct/extensions.py
pyaqueduct/schemas/__init__.py
pyaqueduct/schemas/mutations.py
pyaqueduct/schemas/queries.py
pyaqueduct/settings.py
pyaqueduct-0.1.0.dist-info/LICENSE
pyaqueduct-0.1.0.dist-info/METADATA
pyaqueduct-0.1.0.dist-info/WHEEL
pyaqueduct-0.1.0.dist-info/RECORD
