Metadata-Version: 2.1
Name: pyaqueduct
Version: 0.1.0
Summary: Aqueduct Python Client Library
Home-page: https://aqueducthub.github.io/pyaqueduct
License: MIT
Author: Aqueduct Team
Author-email: aqueduct@riverlane.com
Requires-Python: >=3.8,<3.12
Classifier: License :: OSI Approved :: MIT License
Classifier: Programming Language :: Python :: 3
Classifier: Programming Language :: Python :: 3.8
Classifier: Programming Language :: Python :: 3.9
Classifier: Programming Language :: Python :: 3.10
Classifier: Programming Language :: Python :: 3.11
Requires-Dist: gql[httpx] (>=3.5,<4.0)
Requires-Dist: httpx (>=0.15,<0.25)
Requires-Dist: pydantic (>=2.0,<3.0)
Requires-Dist: pydantic-settings (>=2.2,<3.0)
Requires-Dist: requests (>=2.31,<3.0)
Requires-Dist: tqdm (>=4.66,<5.0)
Requires-Dist: types-tqdm (>=4.66,<5.0)
Project-URL: Documentation, https://aqueducthub.github.io/pyaqueduct
Project-URL: Issues, https://github.com/AqueductHub/pyaqueduct/issues
Project-URL: Repository, https://github.com/AqueductHub/pyaqueduct
